mlcube_singularity/__init__.py
mlcube_singularity/__main__.py
mlcube_singularity/singularity_run.py
mlcube_singularity/tests/__init__.py
mlcube_singularity/tests/test_config.py
mlcube_singularity/tests/test_factory_fn.py
mlcube_singularity/tests/test_singularity_runner.py
mlcube_singularity-0.0.9.dist-info/METADATA
mlcube_singularity-0.0.9.dist-info/WHEEL
mlcube_singularity-0.0.9.dist-info/entry_points.txt
mlcube_singularity-0.0.9.dist-info/top_level.txt
mlcube_singularity-0.0.9.dist-info/RECORD
