Metadata-Version: 2.1
Name: mlcube-singularity
Version: 0.0.9
License: Apache 2.0
Requires-Python: >=3.6
Requires-Dist: mlcube (==0.0.9)
Requires-Dist: spython (==0.2.1)
